openflowthrough/__init__.py
openflowthrough/main.py
openflowthrough/json/fsm.json
openflowthrough-0.1.1.dist-info/AUTHORS.rst
openflowthrough-0.1.1.dist-info/LICENSE
openflowthrough-0.1.1.dist-info/METADATA
openflowthrough-0.1.1.dist-info/WHEEL
openflowthrough-0.1.1.dist-info/top_level.txt
openflowthrough-0.1.1.dist-info/RECORD
